redis_msg_center/__init__.py
redis_msg_center/core.py
redis_msg_center/layers/audio_stream_layer.py
redis_msg_center/layers/msg_layer.py
redis_msg_center/layers/video_stream_layer.py
redis_msg_center-0.1.0.dist-info/METADATA
redis_msg_center-0.1.0.dist-info/WHEEL
redis_msg_center-0.1.0.dist-info/entry_points.txt
redis_msg_center-0.1.0.dist-info/RECORD
